atlassianhw/__init__.py
atlassianhw/_modidx.py
atlassianhw/data.py
atlassianhw/utils.py
atlassianhw/_data/Employee_details.xlsx
atlassianhw/_data/Glossary.xlsx
atlassianhw/_data/Manager_details.xlsx
atlassianhw/_data/Manager_mapping.xlsx
atlassianhw/_data/promo_meta_data.xlsx
atlassianhw-0.0.3.dist-info/LICENSE
atlassianhw-0.0.3.dist-info/METADATA
atlassianhw-0.0.3.dist-info/WHEEL
atlassianhw-0.0.3.dist-info/entry_points.txt
atlassianhw-0.0.3.dist-info/top_level.txt
atlassianhw-0.0.3.dist-info/RECORD
