Metadata-Version: 2.1
Name: atlassianhw
Version: 0.0.3
Summary: Atlassian application homework
Home-page: https://github.com/jazon33y/atlassianhw
Author: jason
Author-email: jazon33y@gmail.com
License: Apache Software License 2.0
Keywords: nbdev jupyter notebook python
Classifier: Development Status :: 4 - Beta
Classifier: Intended Audience :: Developers
Classifier: Natural Language :: English
Classifier: Programming Language :: Python :: 3.7
Classifier: Programming Language :: Python :: 3.8
Classifier: Programming Language :: Python :: 3.9
Classifier: Programming Language :: Python :: 3.10
Classifier: License :: OSI Approved :: Apache Software License
Requires-Python: >=3.7
License-File: LICENSE
Requires-Dist: fastcore
Requires-Dist: pandas
Requires-Dist: numpy
Requires-Dist: nbdev
Requires-Dist: matplotlib
Requires-Dist: seaborn
Requires-Dist: duckdb
Requires-Dist: openpyxl
Requires-Dist: jupyter
Provides-Extra: dev
